{
  "_class": "symbolInstance",
  "booleanOperation": 0,
  "clippingMaskMode": 0,
  "do_objectID": "9587EF87-BB28-4962-9EF3-0570B5A2E37F",
  "exportOptions": {
    "_class": "exportOptions",
    "do_objectID": "EC3DEA7A-E102-41F1-BA5E-BE786621FAD1",
    "exportFormats": [
    ],
    "includedLayerIds": [
    ],
    "layerOptions": 0,
    "shouldTrim": false
  },
  "frame": {
    "_class": "rect",
    "constrainProportions": false,
    "do_objectID": "2311F7B1-B894-406E-B3F1-F57B1828CA0A",
    "height": 801,
    "width": 1280,
    "x": 0,
    "y": 0
  },
  "hasClippingMask": false,
  "horizontalSpacing": 0,
  "isFixedToViewport": false,
  "isFlippedHorizontal": false,
  "isFlippedVertical": false,
  "isLocked": true,
  "isVisible": true,
  "layerListExpandedType": 0,
  "name": "Background",
  "nameIsFixed": false,
  "overrideValues": [
  ],
  "resizingConstraint": 63,
  "resizingType": 0,
  "rotation": 0,
  "scale": 1,
  "shouldBreakMaskChain": false,
  "style": {
    "_class": "style",
    "do_objectID": "4443D67B-4CB1-4522-9253-B562EE9C7D2F",
    "endMarkerType": 0,
    "miterLimit": 10,
    "startMarkerType": 0,
    "windingRule": 1
  },
  "symbolID": "0B3FF9F4-7529-4D4E-92B2-64F25D33036D",
  "verticalSpacing": 0
}