{
  "_class": "text",
  "attributedString": {
    "_class": "attributedString",
    "attributes": [
      {
        "_class": "stringAttribute",
        "attributes": {
          "MSAttributedStringColorAttribute": {
            "_class": "color",
            "alpha": 1,
            "blue": 0.44,
            "green": 0.3528066666666667,
            "red": 0.2596
          },
          "MSAttributedStringFontAttribute": {
            "_class": "fontDescriptor",
            "attributes": {
              "name": "Play-Regular",
              "size": 12
            }
          },
          "kerning": 0,
          "paragraphStyle": {
            "_class": "paragraphStyle",
            "alignment": 0,
            "lineHeightMultiple": 1,
            "maximumLineHeight": 16,
            "minimumLineHeight": 16
          },
          "strikethroughStyle": 0,
          "underlineStyle": 0
        },
        "length": 17,
        "location": 0
      }
    ],
    "string": "7/2/2018 17:13:33"
  },
  "automaticallyDrawOnUnderlyingPath": false,
  "booleanOperation": 0,
  "clippingMaskMode": 0,
  "do_objectID": "DEFBB3BD-9ABE-42AC-BEC8-678AA1800BB4",
  "dontSynchroniseWithSymbol": false,
  "exportOptions": {
    "_class": "exportOptions",
    "do_objectID": "D86388BA-C85E-42C9-941A-026C6C6A3844",
    "exportFormats": [
    ],
    "includedLayerIds": [
    ],
    "layerOptions": 0,
    "shouldTrim": false
  },
  "frame": {
    "_class": "rect",
    "constrainProportions": false,
    "do_objectID": "13B9E76C-C060-4B03-8939-3CEFB5FF4841",
    "height": 16,
    "width": 103,
    "x": 584,
    "y": 52
  },
  "glyphBounds": "{{0, 4}, {102, 9}}",
  "hasClippingMask": false,
  "isFixedToViewport": false,
  "isFlippedHorizontal": false,
  "isFlippedVertical": false,
  "isLocked": false,
  "isVisible": true,
  "layerListExpandedType": 0,
  "lineSpacingBehaviour": 2,
  "name": "7/2/2018 17:13:33",
  "nameIsFixed": false,
  "resizingConstraint": 47,
  "resizingType": 0,
  "rotation": 0,
  "sharedStyleID": "2E0773D9-C86E-4AAD-833C-BE7EDE3B58EE",
  "shouldBreakMaskChain": false,
  "style": {
    "_class": "style",
    "do_objectID": "CA7BE3FB-A338-456F-B320-0037D6AEEF9D",
    "endMarkerType": 0,
    "miterLimit": 10,
    "startMarkerType": 0,
    "textStyle": {
      "_class": "textStyle",
      "do_objectID": "BCB18A5F-890B-4186-A82B-91CC290D134C",
      "encodedAttributes": {
        "MSAttributedStringColorAttribute": {
          "_class": "color",
          "alpha": 1,
          "blue": 0.44,
          "green": 0.3528066666666667,
          "red": 0.2596
        },
        "MSAttributedStringFontAttribute": {
          "_class": "fontDescriptor",
          "attributes": {
            "name": "Play-Regular",
            "size": 12
          }
        },
        "kerning": 0,
        "paragraphStyle": {
          "_class": "paragraphStyle",
          "alignment": 0,
          "lineHeightMultiple": 1,
          "maximumLineHeight": 16,
          "minimumLineHeight": 16
        },
        "strikethroughStyle": 0,
        "underlineStyle": 0
      },
      "verticalAlignment": 0
    },
    "windingRule": 1
  },
  "textBehaviour": 0,
  "userInfo": {
    "com.animaapp.stc-sketch-plugin": {
      "kModelPropertiesKey": {
        "isAutoWidth": 1
      }
    }
  }
}