{
  "_class": "symbolInstance",
  "booleanOperation": 0,
  "clippingMaskMode": 0,
  "do_objectID": "49C3B219-4776-43BE-8B9A-DA03FE1B3903",
  "exportOptions": {
    "_class": "exportOptions",
    "do_objectID": "2CDB5A38-AC16-44C4-B2B9-076E69F5D860",
    "exportFormats": [
    ],
    "includedLayerIds": [
    ],
    "layerOptions": 0,
    "shouldTrim": false
  },
  "frame": {
    "_class": "rect",
    "constrainProportions": false,
    "do_objectID": "83ACC943-3C6A-4B29-9379-2253283561B1",
    "height": 32,
    "width": 72,
    "x": 397,
    "y": 16
  },
  "hasClippingMask": false,
  "horizontalSpacing": 0,
  "isFixedToViewport": false,
  "isFlippedHorizontal": false,
  "isFlippedVertical": false,
  "isLocked": false,
  "isVisible": true,
  "layerListExpandedType": 0,
  "name": "Cancel",
  "nameIsFixed": true,
  "overrideValues": [
    {
      "_class": "overrideValue",
      "overrideName": "9ED4DBDE-1A49-414C-9E20-12DBECA9C1C6_stringValue",
      "value": "Cancel"
    }
  ],
  "resizingConstraint": 44,
  "resizingType": 0,
  "rotation": 0,
  "scale": 1,
  "shouldBreakMaskChain": false,
  "style": {
    "_class": "style",
    "do_objectID": "9A5AFFD3-42FC-4B49-BBD7-2AABA1B43A73",
    "endMarkerType": 0,
    "miterLimit": 10,
    "startMarkerType": 0,
    "windingRule": 1
  },
  "symbolID": "C0E2B08A-47E6-4FBA-9CC1-FFB1AB4CA75D",
  "userInfo": {
    "com.animaapp.stc-sketch-plugin": {
      "kModelPropertiesKey": {
      }
    }
  },
  "verticalSpacing": 0
}