{
  "_class": "text",
  "attributedString": {
    "_class": "attributedString",
    "attributes": [
      {
        "_class": "stringAttribute",
        "attributes": {
          "MSAttributedStringColorAttribute": {
            "_class": "color",
            "alpha": 1,
            "blue": 0.2902374565601349,
            "green": 0.2901752889156342,
            "red": 0.290221631526947
          },
          "MSAttributedStringFontAttribute": {
            "_class": "fontDescriptor",
            "attributes": {
              "name": "Play-Regular",
              "size": 12
            }
          },
          "MSAttributedStringTextTransformAttribute": 1,
          "paragraphStyle": {
            "_class": "paragraphStyle",
            "alignment": 0,
            "allowsDefaultTighteningForTruncation": 0,
            "paragraphSpacing": 20.2176
          }
        },
        "length": 11,
        "location": 0
      }
    ],
    "string": "0x92dF…56E5"
  },
  "automaticallyDrawOnUnderlyingPath": false,
  "booleanOperation": 0,
  "clippingMaskMode": 0,
  "do_objectID": "F80F8BD4-1B54-4144-B7AB-D38DA622D22A",
  "dontSynchroniseWithSymbol": false,
  "exportOptions": {
    "_class": "exportOptions",
    "do_objectID": "8BAD4B90-4630-4017-B02D-8E2193278BA8",
    "exportFormats": [
    ],
    "includedLayerIds": [
    ],
    "layerOptions": 0,
    "shouldTrim": false
  },
  "frame": {
    "_class": "rect",
    "constrainProportions": false,
    "do_objectID": "0B390F43-C24A-4F92-B259-8B56A0E63435",
    "height": 14,
    "width": 87.61814744801495,
    "x": 0,
    "y": 28
  },
  "glyphBounds": "{{0, 3}, {79, 9}}",
  "hasClippingMask": false,
  "isFixedToViewport": false,
  "isFlippedHorizontal": false,
  "isFlippedVertical": false,
  "isLocked": false,
  "isVisible": true,
  "layerListExpandedType": 0,
  "lineSpacingBehaviour": 2,
  "name": "0x92dF…56E5",
  "nameIsFixed": false,
  "resizingConstraint": 47,
  "resizingType": 0,
  "rotation": 0,
  "sharedStyleID": "2BE974FE-23E4-431E-8EE2-CFA142541584",
  "shouldBreakMaskChain": false,
  "style": {
    "_class": "style",
    "blur": {
      "_class": "blur",
      "center": "{0.5, 0.5}",
      "do_objectID": "B931C1E5-181B-4282-9131-13BECB41F6B5",
      "isEnabled": false,
      "motionAngle": 0,
      "radius": 7.776000000000001,
      "saturation": 1,
      "type": 0
    },
    "do_objectID": "DA428B01-E58B-47C8-BD85-564FB179D4AE",
    "endMarkerType": 0,
    "miterLimit": 10,
    "startMarkerType": 0,
    "textStyle": {
      "_class": "textStyle",
      "do_objectID": "2E5A5DA2-8B7E-4545-AAF2-3AEAC65BC9DD",
      "encodedAttributes": {
        "MSAttributedStringColorAttribute": {
          "_class": "color",
          "alpha": 1,
          "blue": 0.2902374565601349,
          "green": 0.2901752889156342,
          "red": 0.290221631526947
        },
        "MSAttributedStringFontAttribute": {
          "_class": "fontDescriptor",
          "attributes": {
            "name": "Play-Regular",
            "size": 12
          }
        },
        "MSAttributedStringTextTransformAttribute": 1,
        "paragraphStyle": {
          "_class": "paragraphStyle",
          "alignment": 0,
          "allowsDefaultTighteningForTruncation": 0,
          "paragraphSpacing": 20.2176
        }
      },
      "verticalAlignment": 0
    },
    "windingRule": 1
  },
  "textBehaviour": 1
}