{
  "_class": "group",
  "booleanOperation": -1,
  "clippingMaskMode": 0,
  "do_objectID": "90B51B29-2C63-438F-BEF1-479CB333AF3A",
  "exportOptions": {
    "_class": "exportOptions",
    "exportFormats": [
    ],
    "includedLayerIds": [
    ],
    "layerOptions": 0,
    "shouldTrim": false
  },
  "frame": {
    "_class": "rect",
    "constrainProportions": false,
    "height": 30,
    "width": 1043,
    "x": 224,
    "y": 5
  },
  "groupLayout": {
    "_class": "MSImmutableFreeformGroupLayout"
  },
  "hasClickThrough": false,
  "hasClippingMask": false,
  "isFixedToViewport": false,
  "isFlippedHorizontal": false,
  "isFlippedVertical": false,
  "isLocked": false,
  "isVisible": true,
  "layerListExpandedType": 2,
  "layers": [
    {
      "class": "symbolInstance",
      "id": "BBEF8001-57D6-4868-B328-6F877EFD20CE"
    },
    {
      "class": "symbolInstance",
      "id": "4E36A822-31CB-4F3A-9E3C-20D3C15E3D6A"
    },
    {
      "class": "symbolInstance",
      "id": "8167B539-E33E-4719-8303-1A01E71B8642"
    },
    {
      "class": "group",
      "id": "79321D6E-33F5-49D5-A8AD-76EFD84DFBBA"
    }
  ],
  "name": "Group 14",
  "nameIsFixed": false,
  "resizingConstraint": 63,
  "resizingType": 0,
  "rotation": 0,
  "shouldBreakMaskChain": false,
  "style": {
    "_class": "style",
    "endMarkerType": 0,
    "miterLimit": 10,
    "startMarkerType": 0,
    "windingRule": 1
  }
}