{
  "_class": "shapePath",
  "booleanOperation": -1,
  "clippingMaskMode": 0,
  "do_objectID": "DB73CAF0-A6AD-4C35-A1D8-B0A439230836",
  "edited": true,
  "exportOptions": {
    "_class": "exportOptions",
    "exportFormats": [
    ],
    "includedLayerIds": [
    ],
    "layerOptions": 0,
    "shouldTrim": false
  },
  "frame": {
    "_class": "rect",
    "constrainProportions": false,
    "height": 39.00549450549426,
    "width": 24.7319615912208,
    "x": 128.2864197530864,
    "y": 179.9703296703297
  },
  "hasClippingMask": false,
  "isClosed": true,
  "isFixedToViewport": false,
  "isFlippedHorizontal": false,
  "isFlippedVertical": false,
  "isLocked": false,
  "isVisible": true,
  "layerListExpandedType": 1,
  "name": "Shape",
  "nameIsFixed": false,
  "pointRadiusBehaviour": 1,
  "points": [
    {
      "_class": "curvePoint",
      "cornerRadius": 0,
      "curveFrom": "{0.73865199449793661, 1.0000000000000007}",
      "curveMode": 1,
      "curveTo": "{0.73865199449793661, 1.0000000000000007}",
      "hasCurveFrom": false,
      "hasCurveTo": false,
      "point": "{0.73865199449793661, 1.0000000000000007}"
    },
    {
      "_class": "curvePoint",
      "cornerRadius": 0,
      "curveFrom": "{1.0000000000000002, 0.54672489082969489}",
      "curveMode": 1,
      "curveTo": "{1.0000000000000002, 0.54672489082969489}",
      "hasCurveFrom": false,
      "hasCurveTo": false,
      "point": "{1.0000000000000002, 0.54672489082969489}"
    },
    {
      "_class": "curvePoint",
      "cornerRadius": 0,
      "curveFrom": "{0.1843191196698761, 0}",
      "curveMode": 1,
      "curveTo": "{0.1843191196698761, 0}",
      "hasCurveFrom": false,
      "hasCurveTo": false,
      "point": "{0.1843191196698761, 0}"
    },
    {
      "_class": "curvePoint",
      "cornerRadius": 0,
      "curveFrom": "{0, 0.54672489082969489}",
      "curveMode": 1,
      "curveTo": "{0, 0.54672489082969489}",
      "hasCurveFrom": false,
      "hasCurveTo": false,
      "point": "{0, 0.54672489082969489}"
    }
  ],
  "resizingConstraint": 63,
  "resizingType": 0,
  "rotation": 0,
  "shouldBreakMaskChain": false,
  "style": {
    "_class": "style",
    "borderOptions": {
      "_class": "borderOptions",
      "dashPattern": [
      ],
      "isEnabled": false,
      "lineCapStyle": 1,
      "lineJoinStyle": 1
    },
    "borders": [
      {
        "_class": "border",
        "color": {
          "_class": "color",
          "alpha": 1,
          "blue": 0.1568627450980392,
          "green": 0.3882352941176471,
          "red": 0.803921568627451
        },
        "fillType": 0,
        "isEnabled": true,
        "position": 0,
        "thickness": 1
      }
    ],
    "endMarkerType": 0,
    "fills": [
      {
        "_class": "fill",
        "color": {
          "_class": "color",
          "alpha": 1,
          "blue": 0.1568627450980392,
          "green": 0.3882352941176471,
          "red": 0.803921568627451
        },
        "fillType": 0,
        "isEnabled": true,
        "noiseIndex": 0,
        "noiseIntensity": 0,
        "patternFillType": 1,
        "patternTileScale": 1
      }
    ],
    "miterLimit": 10,
    "startMarkerType": 0,
    "windingRule": 0
  }
}