{
  "_class": "group",
  "booleanOperation": 0,
  "clippingMaskMode": 0,
  "do_objectID": "59922C79-58D8-4E51-A90D-727E369F6E93",
  "exportOptions": {
    "_class": "exportOptions",
    "exportFormats": [
    ],
    "includedLayerIds": [
    ],
    "layerOptions": 0,
    "shouldTrim": false
  },
  "frame": {
    "_class": "rect",
    "constrainProportions": false,
    "height": 79.37362637362637,
    "width": 67.69821673525406,
    "x": 0,
    "y": 0
  },
  "groupLayout": {
    "_class": "MSImmutableFreeformGroupLayout"
  },
  "hasClickThrough": false,
  "hasClippingMask": false,
  "isFixedToViewport": false,
  "isFlippedHorizontal": false,
  "isFlippedVertical": false,
  "isLocked": false,
  "isVisible": true,
  "layerListExpandedType": 0,
  "layers": [
    {
      "class": "shapePath",
      "id": "338A5FBF-26FF-4733-85A6-AEF358C8CA47"
    },
    {
      "class": "shapePath",
      "id": "19AC4634-2529-47D2-8E0F-1198F37795A4"
    },
    {
      "class": "shapePath",
      "id": "E5EA6E44-5E13-4C9C-9CC7-C4A92F5BCE78"
    },
    {
      "class": "shapePath",
      "id": "503D17BF-D2AB-4D9E-B320-48D09FC5D240"
    },
    {
      "class": "shapePath",
      "id": "1E0CA2A0-20C1-4102-A3F4-2FA0DB941AC7"
    },
    {
      "class": "shapePath",
      "id": "5D5394F3-9BF3-47FF-9107-FD4EDF6CA3D5"
    },
    {
      "class": "shapePath",
      "id": "004236A2-D8E1-48FA-BD4D-C26B35222845"
    },
    {
      "class": "shapePath",
      "id": "8B4337C5-D42F-4CBE-A54B-F98A849CFF23"
    },
    {
      "class": "shapePath",
      "id": "6F4F9F56-B1FA-4E31-A39F-F98F45FF83FA"
    },
    {
      "class": "shapePath",
      "id": "5C6E83D4-8008-48E2-9AF2-CE0C1651F97E"
    },
    {
      "class": "shapePath",
      "id": "6D5D17AD-5590-4E6B-9465-E30AB6FB2F64"
    },
    {
      "class": "shapePath",
      "id": "20111870-FB06-4421-8BE1-15EA396503F1"
    },
    {
      "class": "shapePath",
      "id": "8C0DB0A6-0351-4501-93E7-9E1402727D3E"
    },
    {
      "class": "shapePath",
      "id": "0A799EAA-2DE8-4F87-9756-0ED41053BE9D"
    },
    {
      "class": "shapePath",
      "id": "A55432FB-14CA-4A59-B8BE-5BE3D2A02BC7"
    },
    {
      "class": "shapePath",
      "id": "AB73CFD5-E60A-4621-9BB3-F229D385D122"
    },
    {
      "class": "shapePath",
      "id": "D02B50AA-F33B-447D-BE7F-CF852836EABA"
    },
    {
      "class": "shapePath",
      "id": "8DDB39FF-820A-4EBF-8826-28BE78C47EF1"
    },
    {
      "class": "shapePath",
      "id": "CDBE895C-6575-4303-ACCF-900E52A727FF"
    },
    {
      "class": "shapePath",
      "id": "09E2DEAB-CE44-48D4-9567-54C49CB38B2E"
    },
    {
      "class": "shapePath",
      "id": "C6F06978-29AF-47D6-BE19-0F7C9FBABD25"
    }
  ],
  "name": "Group",
  "nameIsFixed": false,
  "resizingConstraint": 63,
  "resizingType": 0,
  "rotation": 0,
  "shouldBreakMaskChain": false,
  "style": {
    "_class": "style",
    "endMarkerType": 0,
    "fills": [
      {
        "_class": "fill",
        "color": {
          "_class": "color",
          "alpha": 1,
          "blue": 0,
          "green": 0,
          "red": 0
        },
        "fillType": 0,
        "isEnabled": true,
        "noiseIndex": 0,
        "noiseIntensity": 0,
        "patternFillType": 1,
        "patternTileScale": 1
      }
    ],
    "miterLimit": 10,
    "startMarkerType": 0,
    "windingRule": 1
  }
}