{
  "_class": "group",
  "booleanOperation": -1,
  "clippingMaskMode": 0,
  "do_objectID": "A1093B5A-D230-4EE1-98B5-A3DA68F9C548",
  "exportOptions": {
    "_class": "exportOptions",
    "do_objectID": "3EBFFAAC-D87F-4B5D-B4F5-A9D4773FD1C2",
    "exportFormats": [
    ],
    "includedLayerIds": [
    ],
    "layerOptions": 0,
    "shouldTrim": false
  },
  "frame": {
    "_class": "rect",
    "constrainProportions": false,
    "do_objectID": "0EF592B7-167E-49B0-830B-95E0D3AA02CE",
    "height": 17,
    "width": 40,
    "x": 0,
    "y": 0
  },
  "groupLayout": {
    "_class": "MSImmutableFreeformGroupLayout"
  },
  "hasClickThrough": false,
  "hasClippingMask": false,
  "isFixedToViewport": false,
  "isFlippedHorizontal": false,
  "isFlippedVertical": false,
  "isLocked": false,
  "isVisible": true,
  "layerListExpandedType": 0,
  "layers": [
    {
      "class": "rectangle",
      "id": "175320B1-53F2-4E6B-91ED-9828A61A4ABC"
    },
    {
      "class": "text",
      "id": "35E62BBE-76BA-47F0-B590-4BF5108274E8"
    }
  ],
  "name": "Group 10",
  "nameIsFixed": false,
  "resizingConstraint": 63,
  "resizingType": 0,
  "rotation": 0,
  "shouldBreakMaskChain": false,
  "style": {
    "_class": "style",
    "do_objectID": "50B4F14F-3A4D-4C4D-AB8B-42C8321DB752",
    "endMarkerType": 0,
    "miterLimit": 10,
    "startMarkerType": 0,
    "windingRule": 1
  }
}