{
  "_class": "shapePath",
  "booleanOperation": -1,
  "clippingMaskMode": 0,
  "do_objectID": "A5CB6C51-8C0E-4339-B1FC-87312DEA56ED",
  "edited": true,
  "exportOptions": {
    "_class": "exportOptions",
    "do_objectID": "218F10B2-245B-4787-AFE8-96CB93585789",
    "exportFormats": [
    ],
    "includedLayerIds": [
    ],
    "layerOptions": 0,
    "shouldTrim": false
  },
  "frame": {
    "_class": "rect",
    "constrainProportions": false,
    "do_objectID": "776D7186-FD08-4EA4-961A-80DE4000A3AE",
    "height": 12,
    "width": 22,
    "x": 0,
    "y": 0
  },
  "hasClippingMask": false,
  "isClosed": true,
  "isFixedToViewport": false,
  "isFlippedHorizontal": false,
  "isFlippedVertical": false,
  "isLocked": false,
  "isVisible": true,
  "layerListExpandedType": 0,
  "name": "Path",
  "nameIsFixed": false,
  "pointRadiusBehaviour": 0,
  "points": [
    {
      "_class": "curvePoint",
      "cornerRadius": 0,
      "curveFrom": "{0.49227272727272725, 0.13916666666666666}",
      "curveMode": 4,
      "curveTo": "{0.52954545454545454, 0.33333333333333331}",
      "hasCurveFrom": true,
      "hasCurveTo": false,
      "point": "{0.52954545454545454, 0.33333333333333331}"
    },
    {
      "_class": "curvePoint",
      "cornerRadius": 0,
      "curveFrom": "{0.12227272727272727, 0}",
      "curveMode": 3,
      "curveTo": "{0.39136363636363636, 0}",
      "hasCurveFrom": true,
      "hasCurveTo": true,
      "point": "{0.27272727272727271, 0}"
    },
    {
      "_class": "curvePoint",
      "cornerRadius": 0,
      "curveFrom": "{0, 0.77583333333333337}",
      "curveMode": 2,
      "curveTo": "{0, 0.22416666666666663}",
      "hasCurveFrom": true,
      "hasCurveTo": true,
      "point": "{0, 0.5}"
    },
    {
      "_class": "curvePoint",
      "cornerRadius": 0,
      "curveFrom": "{0.39136363636363636, 1}",
      "curveMode": 3,
      "curveTo": "{0.12227272727272727, 1}",
      "hasCurveFrom": true,
      "hasCurveTo": true,
      "point": "{0.27272727272727271, 1}"
    },
    {
      "_class": "curvePoint",
      "cornerRadius": 0,
      "curveFrom": "{0.52954545454545454, 0.66666666666666663}",
      "curveMode": 4,
      "curveTo": "{0.49227272727272725, 0.86083333333333323}",
      "hasCurveFrom": false,
      "hasCurveTo": true,
      "point": "{0.52954545454545454, 0.66666666666666663}"
    },
    {
      "_class": "curvePoint",
      "cornerRadius": 0,
      "curveFrom": "{0.72727272727272729, 0.66666666666666663}",
      "curveMode": 1,
      "curveTo": "{0.72727272727272729, 0.66666666666666663}",
      "hasCurveFrom": false,
      "hasCurveTo": false,
      "point": "{0.72727272727272729, 0.66666666666666663}"
    },
    {
      "_class": "curvePoint",
      "cornerRadius": 0,
      "curveFrom": "{0.72727272727272729, 1}",
      "curveMode": 1,
      "curveTo": "{0.72727272727272729, 1}",
      "hasCurveFrom": false,
      "hasCurveTo": false,
      "point": "{0.72727272727272729, 1}"
    },
    {
      "_class": "curvePoint",
      "cornerRadius": 0,
      "curveFrom": "{0.90909090909090906, 1}",
      "curveMode": 1,
      "curveTo": "{0.90909090909090906, 1}",
      "hasCurveFrom": false,
      "hasCurveTo": false,
      "point": "{0.90909090909090906, 1}"
    },
    {
      "_class": "curvePoint",
      "cornerRadius": 0,
      "curveFrom": "{0.90909090909090906, 0.66666666666666663}",
      "curveMode": 1,
      "curveTo": "{0.90909090909090906, 0.66666666666666663}",
      "hasCurveFrom": false,
      "hasCurveTo": false,
      "point": "{0.90909090909090906, 0.66666666666666663}"
    },
    {
      "_class": "curvePoint",
      "cornerRadius": 0,
      "curveFrom": "{1, 0.66666666666666663}",
      "curveMode": 1,
      "curveTo": "{1, 0.66666666666666663}",
      "hasCurveFrom": false,
      "hasCurveTo": false,
      "point": "{1, 0.66666666666666663}"
    },
    {
      "_class": "curvePoint",
      "cornerRadius": 0,
      "curveFrom": "{1, 0.33333333333333331}",
      "curveMode": 1,
      "curveTo": "{1, 0.33333333333333331}",
      "hasCurveFrom": false,
      "hasCurveTo": false,
      "point": "{1, 0.33333333333333331}"
    },
    {
      "_class": "curvePoint",
      "cornerRadius": 0,
      "curveFrom": "{0.52954545454545454, 0.33333333333333331}",
      "curveMode": 1,
      "curveTo": "{0.52954545454545454, 0.33333333333333331}",
      "hasCurveFrom": false,
      "hasCurveTo": false,
      "point": "{0.52954545454545454, 0.33333333333333331}"
    }
  ],
  "resizingConstraint": 63,
  "resizingType": 0,
  "rotation": 0,
  "shouldBreakMaskChain": false,
  "style": {
    "_class": "style",
    "do_objectID": "C4A2ABF9-D6B5-49FB-83DF-4E46A2465C30",
    "endMarkerType": 0,
    "fills": [
      {
        "_class": "fill",
        "color": {
          "_class": "color",
          "alpha": 1,
          "blue": 0,
          "green": 0,
          "red": 0
        },
        "fillType": 0,
        "isEnabled": true,
        "noiseIndex": 0,
        "noiseIntensity": 0,
        "patternFillType": 0,
        "patternTileScale": 1
      }
    ],
    "miterLimit": 10,
    "startMarkerType": 0,
    "windingRule": 1
  }
}