{
  "_class": "shapePath",
  "booleanOperation": -1,
  "clippingMaskMode": 0,
  "do_objectID": "F42A7FD6-B3E1-4762-B636-D9FDFA36FF82",
  "edited": true,
  "exportOptions": {
    "_class": "exportOptions",
    "exportFormats": [
    ],
    "includedLayerIds": [
    ],
    "layerOptions": 0,
    "shouldTrim": false
  },
  "frame": {
    "_class": "rect",
    "constrainProportions": false,
    "height": 105.811767915778,
    "width": 217.5984569025827,
    "x": 0.3228454628469704,
    "y": 0.4926179762256157
  },
  "hasClippingMask": true,
  "isClosed": true,
  "isFixedToViewport": false,
  "isFlippedHorizontal": false,
  "isFlippedVertical": false,
  "isLocked": false,
  "isVisible": true,
  "layerListExpandedType": 1,
  "name": "Clip 180",
  "nameIsFixed": false,
  "pointRadiusBehaviour": 1,
  "points": [
    {
      "_class": "curvePoint",
      "cornerRadius": 0,
      "curveFrom": "{0.25112264766808623, 0}",
      "curveMode": 3,
      "curveTo": "{0.73632404599676127, 0}",
      "hasCurveFrom": true,
      "hasCurveTo": true,
      "point": "{0.41104871824581535, 0}"
    },
    {
      "_class": "curvePoint",
      "cornerRadius": 0,
      "curveFrom": "{0, 0.19914299777063571}",
      "curveMode": 4,
      "curveTo": "{0.10611245976413787, 0.075833116187498148}",
      "hasCurveFrom": false,
      "hasCurveTo": true,
      "point": "{0, 0.19914299777063571}"
    },
    {
      "_class": "curvePoint",
      "cornerRadius": 0,
      "curveFrom": "{0, 0.19914299777063571}",
      "curveMode": 1,
      "curveTo": "{0, 0.19914299777063571}",
      "hasCurveFrom": false,
      "hasCurveTo": false,
      "point": "{0, 0.19914299777063571}"
    },
    {
      "_class": "curvePoint",
      "cornerRadius": 0,
      "curveFrom": "{0.10611245976413787, 0.67325052838819865}",
      "curveMode": 4,
      "curveTo": "{0, 0.79656040997133615}",
      "hasCurveFrom": true,
      "hasCurveTo": false,
      "point": "{0, 0.79656040997133615}"
    },
    {
      "_class": "curvePoint",
      "cornerRadius": 0,
      "curveFrom": "{0.41104871824581535, 0.59741741220070044}",
      "curveMode": 4,
      "curveTo": "{0.25112264766808623, 0.59741741220070044}",
      "hasCurveFrom": false,
      "hasCurveTo": true,
      "point": "{0.41104871824581535, 0.59741741220070044}"
    },
    {
      "_class": "curvePoint",
      "cornerRadius": 0,
      "curveFrom": "{0.57093522414801712, 0.59741741220070044}",
      "curveMode": 4,
      "curveTo": "{0.41104871824581535, 0.59741741220070044}",
      "hasCurveFrom": true,
      "hasCurveTo": false,
      "point": "{0.41104871824581535, 0.59741741220070044}"
    },
    {
      "_class": "curvePoint",
      "cornerRadius": 0,
      "curveFrom": "{0.82209743649163092, 0.79656040997133615}",
      "curveMode": 4,
      "curveTo": "{0.7159454120519656, 0.67325052838819865}",
      "hasCurveFrom": false,
      "hasCurveTo": true,
      "point": "{0.82209743649163092, 0.79656040997133615}"
    },
    {
      "_class": "curvePoint",
      "cornerRadius": 0,
      "curveFrom": "{0.87230783578398829, 0.85470337878919411}",
      "curveMode": 4,
      "curveTo": "{0.82209743649163092, 0.79656040997133615}",
      "hasCurveFrom": true,
      "hasCurveTo": false,
      "point": "{0.82209743649163092, 0.79656040997133615}"
    },
    {
      "_class": "curvePoint",
      "cornerRadius": 0,
      "curveFrom": "{0.94405554880444043, 0.99999999999999911}",
      "curveMode": 4,
      "curveTo": "{0.91379987621908665, 0.92360519991893153}",
      "hasCurveFrom": false,
      "hasCurveTo": true,
      "point": "{0.94405554880444043, 0.99999999999999911}"
    },
    {
      "_class": "curvePoint",
      "cornerRadius": 0,
      "curveFrom": "{0.97129017580846178, 0.93117345609311153}",
      "curveMode": 4,
      "curveTo": "{0.94405554880444043, 0.99999999999999911}",
      "hasCurveFrom": true,
      "hasCurveTo": false,
      "point": "{0.94405554880444043, 0.99999999999999911}"
    },
    {
      "_class": "curvePoint",
      "cornerRadius": 0,
      "curveFrom": "{0.99654939508437168, 0.77743999536755481}",
      "curveMode": 4,
      "curveTo": "{0.98942492744121124, 0.85630157213584579}",
      "hasCurveFrom": false,
      "hasCurveTo": true,
      "point": "{0.99654939508437168, 0.77743999536755481}"
    },
    {
      "_class": "curvePoint",
      "cornerRadius": 0,
      "curveFrom": "{0.99654939508437168, 0.77743999536755481}",
      "curveMode": 1,
      "curveTo": "{0.99654939508437168, 0.77743999536755481}",
      "hasCurveFrom": false,
      "hasCurveTo": false,
      "point": "{0.99654939508437168, 0.77743999536755481}"
    },
    {
      "_class": "curvePoint",
      "cornerRadius": 0,
      "curveFrom": "{0.99883566812019775, 0.75234951793624549}",
      "curveMode": 4,
      "curveTo": "{0.99654939508437168, 0.77728365036625235}",
      "hasCurveFrom": true,
      "hasCurveTo": false,
      "point": "{0.99654939508437168, 0.77728365036625235}"
    },
    {
      "_class": "curvePoint",
      "cornerRadius": 0,
      "curveFrom": "{1, 0.70128839862184733}",
      "curveMode": 4,
      "curveTo": "{1, 0.72694055994672613}",
      "hasCurveFrom": false,
      "hasCurveTo": true,
      "point": "{1, 0.70128839862184733}"
    },
    {
      "_class": "curvePoint",
      "cornerRadius": 0,
      "curveFrom": "{1, 0.31400445872781452}",
      "curveMode": 4,
      "curveTo": "{1, 0.70128839862184733}",
      "hasCurveFrom": true,
      "hasCurveTo": false,
      "point": "{1, 0.70128839862184733}"
    }
  ],
  "resizingConstraint": 63,
  "resizingType": 0,
  "rotation": 0,
  "shouldBreakMaskChain": false,
  "style": {
    "_class": "style",
    "blur": {
      "_class": "blur",
      "center": "{0.5, 0.5}",
      "isEnabled": false,
      "motionAngle": 0,
      "radius": 6.259125104485929,
      "saturation": 1,
      "type": 0
    },
    "endMarkerType": 0,
    "miterLimit": 10,
    "startMarkerType": 0,
    "windingRule": 1
  }
}