{
  "_class": "text",
  "attributedString": {
    "_class": "attributedString",
    "attributes": [
      {
        "_class": "stringAttribute",
        "attributes": {
          "MSAttributedStringColorAttribute": {
            "_class": "color",
            "alpha": 1,
            "blue": 0.2588235294117647,
            "green": 0.2196078431372549,
            "red": 0.1803921568627451
          },
          "MSAttributedStringFontAttribute": {
            "_class": "fontDescriptor",
            "attributes": {
              "name": "Play-Regular",
              "size": 14
            }
          },
          "paragraphStyle": {
            "_class": "paragraphStyle",
            "alignment": 0,
            "allowsDefaultTighteningForTruncation": 0,
            "paragraphSpacing": 26
          }
        },
        "length": 1,
        "location": 0
      }
    ],
    "string": " "
  },
  "automaticallyDrawOnUnderlyingPath": false,
  "booleanOperation": 0,
  "clippingMaskMode": 0,
  "do_objectID": "5FF19B37-81AD-462E-8AC4-884BDCA89065",
  "dontSynchroniseWithSymbol": false,
  "exportOptions": {
    "_class": "exportOptions",
    "do_objectID": "CFBCAC72-1BAC-42B6-9B4F-CFA513467A72",
    "exportFormats": [
    ],
    "includedLayerIds": [
    ],
    "layerOptions": 0,
    "shouldTrim": false
  },
  "frame": {
    "_class": "rect",
    "constrainProportions": false,
    "do_objectID": "C261EDA6-1CD6-476D-B897-8321FF72861C",
    "height": 16,
    "width": 4,
    "x": 97,
    "y": 2
  },
  "glyphBounds": "{{0, 13}, {0, 0}}",
  "hasClippingMask": false,
  "isFixedToViewport": false,
  "isFlippedHorizontal": false,
  "isFlippedVertical": false,
  "isLocked": false,
  "isVisible": true,
  "layerListExpandedType": 0,
  "lineSpacingBehaviour": 2,
  "name": "↳Description",
  "nameIsFixed": true,
  "resizingConstraint": 11,
  "resizingType": 0,
  "rotation": 0,
  "sharedStyleID": "774C6E91-83EC-4C36-A582-AF414BCB02FB",
  "shouldBreakMaskChain": false,
  "style": {
    "_class": "style",
    "do_objectID": "9E9A29DD-3B00-45DE-8328-696C185698BE",
    "endMarkerType": 0,
    "miterLimit": 10,
    "startMarkerType": 0,
    "textStyle": {
      "_class": "textStyle",
      "do_objectID": "EE2E5653-E03C-41EC-8A02-E619DEB53F3B",
      "encodedAttributes": {
        "MSAttributedStringColorAttribute": {
          "_class": "color",
          "alpha": 1,
          "blue": 0.2588235294117647,
          "green": 0.2196078431372549,
          "red": 0.1803921568627451
        },
        "MSAttributedStringFontAttribute": {
          "_class": "fontDescriptor",
          "attributes": {
            "name": "Play-Regular",
            "size": 14
          }
        },
        "paragraphStyle": {
          "_class": "paragraphStyle",
          "alignment": 0,
          "allowsDefaultTighteningForTruncation": 0,
          "paragraphSpacing": 26
        }
      },
      "verticalAlignment": 0
    },
    "windingRule": 1
  },
  "textBehaviour": 0,
  "userInfo": {
    "com.animaapp.stc-sketch-plugin": {
      "kModelPropertiesKey": {
        "isAutoWidth": 1
      }
    }
  }
}